combinatorixPy/__init__.py
combinatorixPy/combinatorixPy.py
combinatorixPy-1.12.dist-info/LICENCE
combinatorixPy-1.12.dist-info/METADATA
combinatorixPy-1.12.dist-info/WHEEL
combinatorixPy-1.12.dist-info/top_level.txt
combinatorixPy-1.12.dist-info/RECORD
